zerocdn/__init__.py
ZeroCDN-1.0.6.dist-info/METADATA
ZeroCDN-1.0.6.dist-info/WHEEL
ZeroCDN-1.0.6.dist-info/top_level.txt
ZeroCDN-1.0.6.dist-info/RECORD
