Metadata-Version: 2.1
Name: ZeroCDN
Version: 1.0.6
Summary: ZeroCDN.com API
Home-page: UNKNOWN
Author: dimnissv
License: UNKNOWN
Platform: UNKNOWN
Classifier: Programming Language :: Python :: 3.10
Classifier: Development Status :: 4 - Beta
Classifier: Intended Audience :: Developers
Classifier: License :: OSI Approved
Classifier: License :: OSI Approved :: MIT License
Classifier: Operating System :: OS Independent
Classifier: Topic :: Software Development :: Libraries
Classifier: Typing :: Typed
Requires-Python: >=3.8
Requires-Dist: requests
